Test/__init__.py
Test/tests.py
cuTradeNet/__init__.py
cuTradeNet/Models/Allin.py
cuTradeNet/Models/ChakrabortiChakrabarti.py
cuTradeNet/Models/Constant.py
cuTradeNet/Models/DragulescuYakovenko.py
cuTradeNet/Models/MergerSpinoff.py
cuTradeNet/Models/Model.py
cuTradeNet/Models/YardSale.py
cuTradeNet/Models/__init__.py
cuTradeNet/Models/Kernels/__init__.py
cuTradeNet/Models/Kernels/kAi.py
cuTradeNet/Models/Kernels/kC.py
cuTradeNet/Models/Kernels/kCC.py
cuTradeNet/Models/Kernels/kDY.py
cuTradeNet/Models/Kernels/kMS.py
cuTradeNet/Models/Kernels/kYS.py
cuTradeNet/Models/Utils/ExceptionsManager.py
cuTradeNet/Models/Utils/GraphManager.py
cuTradeNet/Models/Utils/__init__.py
cuTradeNet-0.1.2.dist-info/LICENSE
cuTradeNet-0.1.2.dist-info/METADATA
cuTradeNet-0.1.2.dist-info/WHEEL
cuTradeNet-0.1.2.dist-info/top_level.txt
cuTradeNet-0.1.2.dist-info/RECORD
