Metadata-Version: 2.1
Name: cuTradeNet
Version: 0.1.2
Summary: GPU-Accelerated Kinetic Wealth Exchange Models on Complex Networks
Home-page: https://github.com/Qsanti/cuTradeNet
Author: Santiago Cuevas
Author-email: san.cuevas@protonmail.com
Classifier: Programming Language :: Python :: 3
Classifier: Environment :: GPU :: NVIDIA CUDA
Classifier: Operating System :: OS Independent
Classifier: License :: OSI Approved :: MIT License
Classifier: Intended Audience :: Science/Research
Classifier: Development Status :: 3 - Alpha
License-File: LICENSE
Requires-Dist: numba
Requires-Dist: networkx
Requires-Dist: igraph
